dataclass_to_json/__init__.py
dataclass_to_json/__version__.py
dataclass_to_json/convert_class_to_json.py
dataclass_to_json-1.1.0.dist-info/LICENSE
dataclass_to_json-1.1.0.dist-info/METADATA
dataclass_to_json-1.1.0.dist-info/WHEEL
dataclass_to_json-1.1.0.dist-info/top_level.txt
dataclass_to_json-1.1.0.dist-info/RECORD
