Metadata-Version: 2.1
Name: dataclass-to-json
Version: 1.1.0
Summary: Convert a dataclass structure to a JSON object
Home-page: https://github.com/DninoAdnane/dataclass_to_json
Author: Adnane Guettaf
Author-email: Adnane Guettaf <adnane.guettaf@gmail.com>
Maintainer-email: Adnane Guettaf <adnane.guettaf@gmail.com>
Project-URL: Homepage, https://github.com/DninoAdnane/dataclass_to_json
Project-URL: Issues, https://github.com/DninoAdnane/dataclass_to_json/issues
Classifier: Programming Language :: Python :: 3
Classifier: License :: OSI Approved :: MIT License
Classifier: Operating System :: OS Independent
Classifier: Intended Audience :: Developers
Classifier: Intended Audience :: Information Technology
Classifier: Programming Language :: Python :: 3.8
Classifier: Programming Language :: Python :: 3.9
Classifier: Programming Language :: Python :: 3.10
Classifier: Programming Language :: Python :: 3.11
Classifier: Programming Language :: Python :: 3.12
Requires-Python: >=3.7
License-File: LICENSE
